{
  "English":{
    "name": "English",
    "flag":"theme/img/us.png",
    "chosen": false,
    "words":{
      "Tree":{
        "Dutch":"Boom",
        "Swedish":"Träd"
      }
    }
  },
  "Dutch":{
    "name": "Dutch",
    "flag":"theme/img/nl.png",
    "chosen": false,
    "words":{
      "Boom":{
        "English":"Tree"
      }
    }
  },

  "Swedish":{
    "name": "Swedish",
    "flag":"theme/img/se.png",
    "chosen": true,
    "words":{
      "Träd":{
        "Dutch":"Boom"
      }
    }
  }
}